{"version": "1", "message": "ERROR: Hidden Testcases server unreachable.", "problem_id": "ads1_week3_exam", "user_id": "tezasrivishnu", "score": {"sample": {"0": {"execution_time": 0.27469301223754883, "passed": false}, "1": {"execution_time": 0.23833918571472168, "passed": false}, "2": {"execution_time": 0.23812317848205566, "passed": false}, "3": {"execution_time": 0.23807525634765625, "passed": false}, "4": {"execution_time": 0.24696922302246094, "passed": false}}}, "check_style_score": "0/1"}