{"version": "1", "message": "ERROR: Hidden Testcases server unreachable.", "problem_id": "ads1_week3_exam", "user_id": "tezasrivishnu", "score": {"sample": {"0": {"execution_time": 0.25142812728881836, "passed": false}, "1": {"execution_time": 0.28464794158935547, "passed": false}, "2": {"execution_time": 0.25321221351623535, "passed": false}, "3": {"execution_time": 0.24700260162353516, "passed": false}, "4": {"execution_time": 0.28497958183288574, "passed": false}}}, "check_style_score": "0/1"}